tap_dbf/__init__.py
tap_dbf/__main__.py
tap_dbf/client.py
tap_dbf/tap.py
tap_dbf-0.1.22.dist-info/METADATA
tap_dbf-0.1.22.dist-info/WHEEL
tap_dbf-0.1.22.dist-info/entry_points.txt
tap_dbf-0.1.22.dist-info/licenses/LICENSE
tap_dbf-0.1.22.dist-info/RECORD
