Metadata-Version: 2.4
Name: tap-dbf
Version: 0.1.22
Summary: Singer tap for DBF files
Project-URL: Documentation, https://github.com/reservoir-data/tap-dbf#readme
Project-URL: Homepage, https://github.com/reservoir-data/tap-dbf
Project-URL: Repository, https://github.com/reservoir-data/tap-dbf
Author-email: "Edgar R. Mondragón" <edgarrm358@gmail.com>
Maintainer-email: "Edgar R. Mondragón" <edgarrm358@gmail.com>
License-Expression: Apache-2.0
License-File: LICENSE
Keywords: ELT,dBase,dbf,singer.io
Classifier: Operating System :: OS Independent
Classifier: Programming Language :: Python :: 3 :: Only
Classifier: Programming Language :: Python :: 3.10
Classifier: Programming Language :: Python :: 3.11
Classifier: Programming Language :: Python :: 3.12
Classifier: Programming Language :: Python :: 3.13
Classifier: Programming Language :: Python :: 3.14
Classifier: Programming Language :: Python :: 3.15
Classifier: Topic :: Database
Requires-Python: >=3.10
Requires-Dist: dbfread~=2.0.7
Requires-Dist: fsspec~=2025.9.0
Requires-Dist: singer-sdk~=0.51.0
Provides-Extra: all
Requires-Dist: gcsfs~=2025.9.0; extra == 'all'
Requires-Dist: s3fs~=2025.9.0; extra == 'all'
Provides-Extra: gcs
Requires-Dist: gcsfs~=2025.9.0; extra == 'gcs'
Provides-Extra: s3
Requires-Dist: s3fs~=2025.9.0; extra == 's3'
